rcslice/__init__.py
rcslice/rcslice.py
rcslice/version.py
rcslice-1.1.0.dist-info/METADATA
rcslice-1.1.0.dist-info/RECORD
rcslice-1.1.0.dist-info/WHEEL
rcslice-1.1.0.dist-info/top_level.txt
